fluent_pages/__init__.py
fluent_pages/apps.py
fluent_pages/appsettings.py
fluent_pages/sitemaps.py
fluent_pages/urlresolvers.py
fluent_pages/urls.py
fluent_pages/admin/__init__.py
fluent_pages/admin/utils.py
fluent_pages/adminui/__init__.py
fluent_pages/adminui/htmlpageadmin.py
fluent_pages/adminui/overrides.py
fluent_pages/adminui/pageadmin.py
fluent_pages/adminui/pagelayoutadmin.py
fluent_pages/adminui/urlnodechildadmin.py
fluent_pages/adminui/urlnodeparentadmin.py
fluent_pages/adminui/utils.py
fluent_pages/extensions/__init__.py
fluent_pages/extensions/pagetypebase.py
fluent_pages/extensions/pagetypepool.py
fluent_pages/forms/__init__.py
fluent_pages/forms/fields.py
fluent_pages/integration/__init__.py
fluent_pages/integration/fluent_contents/__init__.py
fluent_pages/integration/fluent_contents/admin.py
fluent_pages/integration/fluent_contents/models.py
fluent_pages/integration/fluent_contents/page_type_plugins.py
fluent_pages/integration/fluent_contents/tests.py
fluent_pages/locale/en/LC_MESSAGES/django.mo
fluent_pages/locale/en/LC_MESSAGES/django.po
fluent_pages/locale/es/LC_MESSAGES/django.mo
fluent_pages/locale/es/LC_MESSAGES/django.po
fluent_pages/locale/nl/LC_MESSAGES/django.mo
fluent_pages/locale/nl/LC_MESSAGES/django.po
fluent_pages/management/__init__.py
fluent_pages/management/commands/__init__.py
fluent_pages/management/commands/make_language_redirects.py
fluent_pages/management/commands/rebuild_page_tree.py
fluent_pages/management/commands/remove_stale_pages.py
fluent_pages/migrations/0001_initial.py
fluent_pages/migrations/0002_add_htmlpage_meta_image.py
fluent_pages/migrations/0003_set_htmlpage_defaults.py
fluent_pages/migrations/0004_add_htmlpage_not_null.py
fluent_pages/migrations/0005_author_on_delete_set_null.py
fluent_pages/migrations/0006_remove_mptt_indices.py
fluent_pages/migrations/0007_use_parler_transactionsfk.py
fluent_pages/migrations/__init__.py
fluent_pages/models/__init__.py
fluent_pages/models/db.py
fluent_pages/models/fields.py
django_fluent_pages-3.0.2.dist-info/AUTHORS
django_fluent_pages-3.0.2.dist-info/LICENSE.rst
django_fluent_pages-3.0.2.dist-info/METADATA
django_fluent_pages-3.0.2.dist-info/WHEEL
django_fluent_pages-3.0.2.dist-info/top_level.txt
django_fluent_pages-3.0.2.dist-info/RECORD
