Metadata-Version: 2.1
Name: django-fluent-pages
Version: 3.0.2
Summary: A flexible, scalable CMS with custom node types, and flexible block content.
Home-page: https://github.com/edoburu/django-fluent-pages
Download-URL: https://github.com/edoburu/django-fluent-pages/zipball/master
Author: Diederik van der Boor
Author-email: opensource@edoburu.nl
License: Apache 2.0
Classifier: Development Status :: 5 - Production/Stable
Classifier: Environment :: Web Environment
Classifier: Intended Audience :: Developers
Classifier: License :: OSI Approved :: Apache Software License
Classifier: Operating System :: OS Independent
Classifier: Programming Language :: Python
Classifier: Programming Language :: Python :: 3.6
Classifier: Programming Language :: Python :: 3.7
Classifier: Programming Language :: Python :: 3.8
Classifier: Programming Language :: Python :: 3.9
Classifier: Framework :: Django
Classifier: Framework :: Django :: 2.2
Classifier: Framework :: Django :: 3.1
Classifier: Framework :: Django :: 3.2
Classifier: Framework :: Django :: 4.0
Classifier: Framework :: Django :: 4.1
Classifier: Framework :: Django :: 4.2
Classifier: Topic :: Internet :: WWW/HTTP
Classifier: Topic :: Internet :: WWW/HTTP :: Dynamic Content
Classifier: Topic :: Software Development :: Libraries :: Application Frameworks
Classifier: Topic :: Software Development :: Libraries :: Python Modules
Requires: Django (>=2.2)
License-File: LICENSE.rst
License-File: AUTHORS
Requires-Dist: django-fluent-utils (>=2.0.1)
Requires-Dist: django-mptt (>=0.10.0)
Requires-Dist: django-parler (>=2.0.1)
Requires-Dist: django-polymorphic (>=2.1.2)
Requires-Dist: django-polymorphic-tree (>=1.5.1)
Requires-Dist: django-slug-preview (>=1.0.4)
Requires-Dist: django-tag-parser (>=3.2)
Requires-Dist: Pillow
Provides-Extra: flatpage
Requires-Dist: django-wysiwyg (>=0.7.1) ; extra == 'flatpage'
Provides-Extra: fluentpage
Requires-Dist: django-fluent-contents (>=2.0.7) ; extra == 'fluentpage'
Provides-Extra: redirectnode
Requires-Dist: django-any-urlfield (>=2.6.2) ; extra == 'redirectnode'
Provides-Extra: tests
Requires-Dist: django-any-urlfield (>=2.6.2) ; extra == 'tests'
Requires-Dist: django-wysiwyg (>=0.7.1) ; extra == 'tests'
Requires-Dist: django-fluent-contents (>=2.0.7) ; extra == 'tests'
